phonexia_denoiser_client.py
phonexia_denoiser_client-2.0.1.dist-info/METADATA
phonexia_denoiser_client-2.0.1.dist-info/WHEEL
phonexia_denoiser_client-2.0.1.dist-info/entry_points.txt
phonexia_denoiser_client-2.0.1.dist-info/top_level.txt
phonexia_denoiser_client-2.0.1.dist-info/RECORD
